plogger/__init__.py
plogger-1.0.8.dist-info/LICENSE
plogger-1.0.8.dist-info/METADATA
plogger-1.0.8.dist-info/WHEEL
plogger-1.0.8.dist-info/top_level.txt
plogger-1.0.8.dist-info/RECORD
