Metadata-Version: 2.1
Name: plogger
Version: 1.0.8
Summary: A simple high level logger wrapper to log into console/file with different level.
Home-page: https://github.com/c-pher/plogger.git
Author: Andrey Komissarov
Author-email: a.komisssarov@gmail.com
License: MIT
Classifier: Programming Language :: Python :: 3
Classifier: License :: OSI Approved :: MIT License
Classifier: Operating System :: OS Independent
Classifier: Intended Audience :: System Administrators
Classifier: Intended Audience :: Developers
Classifier: Natural Language :: English
Classifier: Programming Language :: Python :: 3.6
Classifier: Topic :: System :: Systems Administration
Classifier: Topic :: Software Development :: Libraries :: Python Modules
Requires-Python: >=3.6
License-File: LICENSE
